soft_delete_new/__init__.py
soft_delete_new/models.py
django_softdelete_new-0.2.1.dist-info/LICENSE
django_softdelete_new-0.2.1.dist-info/METADATA
django_softdelete_new-0.2.1.dist-info/WHEEL
django_softdelete_new-0.2.1.dist-info/top_level.txt
django_softdelete_new-0.2.1.dist-info/RECORD
