Metadata-Version: 2.1
Name: django-softdelete-new
Version: 0.2.1
Summary: 基于Django的轻量级软删除插件，支持Django>=1.11
Home-page: https://github.com/aeasringnar/django-softdelete-new
Author: Aeasringnar
Author-email: Aeasringnar@gmail.com
License: MIT License
Platform: UNKNOWN
Classifier: Environment :: Web Environment
Classifier: Framework :: Django
Classifier: Framework :: Django :: 1.11
Classifier: Framework :: Django :: 2.2
Classifier: Framework :: Django :: 3.0
Classifier: Intended Audience :: Developers
Classifier: License :: OSI Approved :: MIT License
Classifier: Programming Language :: Python :: 3
